docskin/__init__.py
docskin/__main__.py
docskin/cli/__init__.py
docskin/cli/commands/__init__.py
docskin/cli/commands/github_issue.py
docskin/cli/commands/markdown_file.py
docskin/cli/commands/markdown_folder.py
docskin/cli/commands/setup.py
docskin/core/__init__.py
docskin/core/content.py
docskin/core/converter.py
docskin/core/github_api.py
docskin/core/setup.py
docskin/core/styles.py
docskin/core/tokens.py
docskin-0.3.0.dist-info/METADATA
docskin-0.3.0.dist-info/WHEEL
docskin-0.3.0.dist-info/entry_points.txt
docskin-0.3.0.dist-info/licenses/LICENSE
docskin-0.3.0.dist-info/RECORD
