Metadata-Version: 2.4
Name: docskin
Version: 0.3.0
Summary: Style your documents - convert Markdown files and GitHub issues into styled PDF documents in your corporate skin.
Author-email: "Constantin v. Deimling" <c.deimling@web.de>
License-File: LICENSE
Requires-Python: >=3.9
Requires-Dist: click>=8.1.8
Requires-Dist: markdown>=3.6
Requires-Dist: pygments>=2.18.0
Requires-Dist: requests>=2.32.3
Requires-Dist: weasyprint>=62.3
